fast_soup/__init__.py
fast_soup-1.1.0.dist-info/LICENSE
fast_soup-1.1.0.dist-info/WHEEL
fast_soup-1.1.0.dist-info/METADATA
fast_soup-1.1.0.dist-info/RECORD
