Metadata-Version: 2.1
Name: fast-soup
Version: 1.1.0
Summary: BeautifulSoup interface for lxml
License: MIT
Author: spumer
Author-email: spumer-tm@yandex.ru
Requires-Python: >=3.6,<4.0
Classifier: License :: OSI Approved :: MIT License
Classifier: Programming Language :: Python :: 3
Classifier: Programming Language :: Python :: 3.6
Classifier: Programming Language :: Python :: 3.7
Classifier: Programming Language :: Python :: 3.8
Requires-Dist: beautifulsoup4 (>=4.3.2,<5.0.0)
Requires-Dist: cssselect (>=1.0.1,<2.0.0)
Requires-Dist: lxml (>=4.5.0,<5.0.0)
